{
  "query": "南京地铁S7号线的运营里程，在南京的已运营地铁线路中长度排第几?",
  "result": [
    {
      "position": 1,
      "content": "2017/07/28\n空轨线\n10.50\n2.10\n悬挂式单轨\n2023/09/26\n8\n南京\n15\n1 号线\n45.42\n1.47\n地铁\n2005/09/03\n2 号线\n43.00\n1.48\n地铁\n2010/05/28\n3 号线\n44.90\n1.60\n地铁\n2015/04/01\n4 号线\n33.80\n1.99\n地铁\n2017/01/18\n5 号线\n12.89\n1.61\n地铁\n2024/03/31\n7 号线\n35.49\n1.37\n地铁\n2022/12/28\n10 号线\n21.60\n1.66\n地铁\n2014/07/01\nS1 号线\n35.80\n4.48\n市域快轨\n2014/07/01\nS3 号线\n37.20\n2.07\n市域快轨\n2017/12/06\nS8 号线\n47.30\n2.63\n市域快轨\n2014/08/01\nS9 号线\n52.40\n10.48\n市域快轨\n2017/12/30\nS7 号线\n30.20\n3.78\n市域快轨"
    },
    {
      "position": 2,
      "content": "7\n0.80\n有轨电车\n2016/03/05\n26\n淮安\n1\n有轨电车1 号线\n20.07\n0.91\n有轨电车\n2015/12/28\n27\n福州\n5\n1 号线\n29.06\n1.21\n地铁\n2016/05/18\n2 号线\n29.35\n1.40\n地铁\n2019/04/26\n4 号线\n22.64\n1.26\n地铁\n2023/08/27\n5 号线\n27.16\n1.43\n地铁\n2022/04/29\n6 号线\n30.73\n2.36\n地铁\n2022/08/28\n28\n东莞\n1\n2 号线\n37.79\n2.70\n地铁\n2016/05/27\n29\n南宁\n5\n1 号线\n31.43\n1.31\n地铁\n2016/06/29\n2 号线\n26.78\n1.22\n地铁\n2017/12/28\n90\n序\n号\n城市\n线路数\n（条 ）\n线路名称\n运营里程\n（公里）\n平均站间距\n（公里）\n制式\n投运时间\n3 号线\n27.23\n1.24\n地铁\n2019/06/06"
    },
    {
      "position": 3,
      "content": "的系统制式来看，5531.60 公里的在实\n施规划线路包含地铁、轻轨、市域快轨、磁浮交通 、有轨电车、\n导轨式胶轮系统、电子导向胶轮系统7 种制式。\n地铁3291.34 公里，占比59.50%，同比下降9.29 个百分\n点；轻轨2.69 公里，占比0.05%，同比下降0.54 个百分点；\n市域快轨1899.81 公里，占比34.35%，同比增加10.37 个百分\n点；磁浮交通53.40 公里，占比0.97%，同比增加0.87 个百分\n点；有轨电车156.73 公里，占比2.83%，同比下降0.90 个百\n分点；导轨式胶轮系统41.72 公里，占比0.75%，同比下降\n0.74 个百分 点；电子导向胶轮系统85.90 公里，占比1.55%，"
    }
  ],
  "answer": "根据提供的上下文信息，南京地铁S7号线的运营里程为30.20公里。在南京已运营的地铁线路中，S7号线的长度排名如下：\n\n1. S9号线：52.40公里\n2. S8号线：47.30公里\n3. 1号线：45.42公里\n4. 2号线 ：43.00公里\n5. 3号线：44.90公里\n6. 4号线：33.80公里\n7. S1号线：35.80公里\n8. S3号线：37.20公里\n9. 7号线：35.49公里\n10. 10号线：21.60公里\n11. S7号线：30.20公里\n12. 5号线：12.89公里（计划2024年3月31日开通，目前未运营）\n\n因此，南京地铁S7号线的运营里程在南京的已运营地铁线路中长度排第10位。"
}